package_main/__init__.py
package_main/main_module.py
package_main-0.1.2.dist-info/METADATA
package_main-0.1.2.dist-info/WHEEL
package_main-0.1.2.dist-info/RECORD
