Metadata-Version: 2.4
Name: package_main
Version: 0.1.2
Summary: Heegoo package example
Author-email: Yang Heegoo <heegoo.yang@gmail.com>
License: MIT
Requires-Python: >=3.8
